{
    "team": [
        {
            "name": "Premawansha L M A H",
            "email": "e19300@eng.pdn.ac.lk",
            "eNumber": "E/19/300"
        },
        {
            "name": "Premachandra K H J D",
            "email": "e19295@eng.pdn.ac.lk",
            "eNumber": "E/19/295"
        },
        {
            "name": "Wimalasiri P M A C",
            "email": "e19452@eng.pdn.ac.lk",
            "eNumber": "E/19/452"
        },
        {
            "name": "Somawansha M V N L",
            "email": "e19492@eng.pdn.ac.lk",
            "eNumber": "E/19/492"
        }
    ],
    "supervisors": [
        {
            "name": "Dr. Eng. Kamalanath Samarakoon",
            "email": "kamalanath@eng.pdn.ac.lk"
        }
    ],
    "tags": ["co227"]
}
